Workbook

Sheet Legend
A1: Traveloure content source index
A2: Seed for the content_sources registry (content-sourcing-brief §5). One row per source. The engine reads sources by NEED, not by site; a source declares what it covers AND what it does not.
A4: How to use this file
A5: 1. Yellow cells are yours to fill: terms_url, terms_checked_at, terms_checked_by, active. A source is never set active until terms are checked and dated.
A6: 2. covers / does_not_cover use the need keys from the Needs sheet, comma-separated. Sub-needs use dots (transport.intercity.rail).
A7: 3. markets: comma-separated market slugs (kyoto, edinburgh, porto, bogota, cartagena, mumbai, goa, jaipur) or 'global'.
A8: 4. adapter: api | affiliate_feed | tavily_extract | tavily_crawl | manual. This is how the fact reaches place_facts; the engine never sees the difference.
A9: 5. license_class: official (public body / operator / venue) | editorial (publication) | partner (affiliate or API agreement) | restricted (usable inside plans only, never public).
A10: 6. Coverage (Kyoto) recomputes from the Sources sheet: a need is a GAP when it is required for the slice and no ACTIVE source covers it for Kyoto or globally.
A11: 7. Off the list by rule: OTAs and review sites (Booking display outside hotel_cache, Expedia, TripAdvisor), Google results at large, resale ticket hosts (R208), any site whose terms forbid automated access.
A13: Status vocabulary
A14: key_status: held (env var name) | pending (applied) | none | n/a
... A26: program_page is where the relationship lives (partner portal, API docs, about page). content_url is the page or endpoint the adapter actually reads facts from. Register content_url, never the homepage. URLs marked 'verify' were written from memory and must be opened before a row goes active; ids in partner URLs (Viator d-ids, GetYourGuide l-ids, Klook city ids) change and must be confirmed.

Sheet Needs
A1: need | B1: what the plan needs to know | C1: required for Kyoto Trips slice | D1: where it is used
A2: lodging | B2: availability, rate, cancellation tier, coordinates | C2: yes | D2: anchor question, compare view (A3/A4)
A3: transport.intercity | B3: rail, bus, ferry, flights between cities | C3: recommended | D3: arrival/departure days
A4: transport.intercity.rail | B4: national/regional rail, passes | C4: recommended | D4: arrival/departure days
A5: transport.intercity.bus | B5: intercity coach | C5: no | D5: arrival/departure days
A6: transport.intercity.ferry | B6: ferries | C6: no | D6: other markets
A7: transport.cruise | B7: river/ocean cruises, ports | C7: no | D7: other markets
A8: transport.local | B8: metro/bus lines, passes, last trains, taxi norms | C8: yes | D8: plan-fit, day feasibility
A9: stop.hours | B9: opening hours, seasonal closures, special openings | C9: yes | D9: every located stop
A10: stop.ticketing | B10: advance-only, sells out by, timed entry, price | C10: yes | D10: temples, museums, shows
A11: dining | B11: reservation policy, hours, price level, dietary | C11: yes | D11: dinner items
A12: activity | B12: tours, classes, experiences, provider terms | C12: yes (platform listings first) | D12: suggestions, bookings
... A15: neighbourhood | B15: character, walkability, what is near | C15: yes | D15: anchor question, compare

Sheet Sources
A1: source_id | B1: name | C1: program_page (partner / API / about) | D1: content_url (what the adapter reads) | E1: kind | F1: adapter | G1: markets | H1: covers | I1: does_not_cover | J1: license_class | K1: key_status | L1: api_status | M1: terms_url | N1: terms_checked_at | O1: terms_checked_by | P1: active | Q1: notes
A2: google_places | B2: Google Places API | C2: https://developers.google.com/maps/documentation/places | D2: API: Places API (New) — Place Details / Nearby Search / Text Search endpoints (no page) | E2: partner api | F2: api | G2: global | H2: stop.hours, dining, neighbourhood | I2: stop.ticketing, event, transport.intercity, transport.local | J2: restricted | K2: held (GOOGLE_MAPS_API_KEY) | L2: live | P2: no | Q2: Structured spine. Display inside plans next to a map only; cache <= 30 days; never a public directory. Enable Places API (New) on the same project as Routes.
A3: google_routes | B3: Google Routes API (Compute Route Matrix) | C3: https://developers.google.com/maps/documentation/routes | D3: API: routes.googleapis.com computeRouteMatrix, travelMode WALK | TRANSIT (no page) | E3: partner api | F3: api | G3: global | H3: transport.local, neighbourhood | I3: transport.local fares & passes, last-service rules, transport.intercity.rail, lodging, activity, dining | J3: restricted | K3: held (GOOGLE_MAPS_API_KEY; Routes API enabled on TLoure 2) | L3: live — first Kyoto refresh 2026-09-29 (128 elements, 64 walk / 64 transit) | P3: no | Q3: Feeds travel_time_matrix (A2). Transit durations come from operators' GTFS via Google. Cache limit is 30 days under Google's terms, which is why the refresh is monthly; do not lengthen it. Money and rules (passes, fares, last trains) come from the city transport source, not from here.
A4: booking_com | B4: Booking.com affiliate | C4: https://www.booking.com/affiliate-program/ | D4: API only via the existing hotel_cache writer (no page crawl; Booking terms forbid it) | E4: partner feed | F4: affiliate_feed | G4: global | H4: lodging | I4: activity, transport.intercity, transport.local, dining | J4: partner | K4: not in production secrets (2026-09-28 list) | L4: writer exists (hotel_cache), 0 Kyoto rows | P4: no | Q4: Feeds hotel_cache. Production census shows 0 Kyoto hotels: secrets missing or API failing; Replit [BookingCom] log check pending.
A5: viator | B5: Viator Partner API | C5: https://partnerresources.viator.com/ | D5: https://www.viator.com/Kyoto/d332-ttd (Kyoto things-to-do; verify destination id) — prefer Partner API | E5: partner api | F5: api | G5: global | H5: activity | I5: lodging, transport.intercity, transport.local, dining, event | J5: partner | K5: held (VIATOR_API_KEY, VIATOR_SANDBOX_API_KEY) | L5: key held; full Partner API access being requested | P5: no | Q5: Tours and experiences. Platform listings rank first; Viator fills gaps. Confirm which tier of access the key grants (affiliate vs merchant).
A6: getyourguide | B6: GetYourGuide Partner | C6: https://partner.getyourguide.com/ | D6: https://www.getyourguide.com/kyoto-l96/ (verify location id) — prefer Partner API once approved | E6: partner api | F6: api | G6: global | H6: activity | I6: lodging, transport.intercity, transport.local, dining | J6: partner | K6: none | L6: apply (Partner API + affiliate) | P6: no | Q6: Strong in Europe (Edinburgh, Porto) and Japan. Apply through the partner portal; API access is by approval.
A7: klook | B7: Klook Affiliate / Partner | C7: https://affiliate.klook.com/ | D7: https://www.klook.com/city/29-kyoto/ (verify city id); JR Pass: https://www.klook.com/activity/1466-jr-pass-whole-japan/ (verify) | E7: partner api | F7: affiliate_feed | G7: kyoto, mumbai, goa, jaipur | H7: activity, stop.ticketing, transport.local, transport.intercity.rail, practicalities | I7: lodging, dining, transport.cruise | J7: partner | K7: none | L7: apply (affiliate program; partner API by application) | P7: no | Q7: Asia-strong. Covers attraction tickets, JR Pass and rail passes, airport transfers, SIM/WiFi. Best current answer for Japan rail passes; JR schedules still need the operator source.
A8: musement | B8: Musement (TUI) | C8: https://www.musement.com/ | D8: https://www.musement.com/us/porto/ ; https://www.musement.com/us/edinburgh/ | E8: partner feed | F8: affiliate_feed | G8: edinburgh, porto | H8: activity, stop.ticketing | I8: lodging, transport.intercity, transport.local, dining | J8: partner | K8: held (MUSEMENT_AFFILIATE_ID) | L8: affiliate id held | P8: no | Q8: Europe-heavy activities and attraction tickets. Low value for Kyoto; keep for Porto and Edinburgh.
A9: 12go | B9: 12Go (via Travelpayouts) | C9: https://12go.asia/ | D9: https://12go.asia/en/travel/kyoto/osaka ; https://12go.asia/en/travel/mumbai/goa ; https://12go.asia/en/travel/delhi/jaipur | E9: partner feed | F9: affiliate_feed | G9: mumbai, goa, jaipur, kyoto | H9: transport.intercity.bus, transport.intercity.ferry, transport.intercity.rail | I9: transport.intercity.rail (Japan JR), transport.cruise, transport.local, lodging, activity | J9: partner | K9: via TRAVELPAYOUTS_TOKEN (held) | L9: confirm 12Go program is enabled in the Travelpayouts account | P9: no | Q9: Bus, ferry and rail booking across South and Southeast Asia (Indian rail included). Does NOT sell JR trains or Japan Rail Pass; Japan coverage is thin. No cruises.
A10: travelpayouts | B10: Travelpayouts network | C10: https://www.travelpayouts.com/ | D10: n/a — network; programs expose their own feeds/links | E10: network | F10: affiliate_feed | G10: global | H10: transport.intercity, lodging, activity | I10: stop.hours, stop.ticketing, dining, transport.local | J10: partner | K10: held (TRAVELPAYOUTS_TOKEN) | L10: live | P10: no | Q10: Aggregator that carries 12Go, GetYourGuide, Klook and others as programs. A network row, not a fact source; register the programs you enable as their own rows.
A11: impact | B11: Impact network (Fever; Ticketmaster pending) | C11: https://app.impact.com/ | D11: Fever content pages: https://feverup.com/en/<city> (Fever has no Kyoto city page; check coverage per market) | E11: network | F11: affiliate_feed | G11: global | H11: event, activity | I11: lodging, transport.intercity, transport.local, dining, stop.hours | J11: partner | K11: held (IMPACT_ACCOUNT_SID, IMPACT_AUTH_TOKEN) | L11: Fever live; Ticketmaster application submitted 2026-09-28 | P11: no | Q11: Fever content comes through here today. Ticketmaster affiliate approval is separate from its Discovery API key.
A12: ticketmaster_discovery | B12: Ticketmaster Discovery API | C12: https://developer.ticketmaster.com/ | D12: API: /discovery/v2/events?latlong=..&radius=30&unit=km (no page) | E12: partner api | F12: api | G12: global | H12: event | I12: lodging, activity, transport.intercity, transport.local, dining, stop.hours | J12: partner | K12: pending (TICKETMASTER_API_KEY not yet set) | L12: self-serve key | P12: no | Q12: Coverage in our eight cities is thin (strong US/UK/parts of Europe; weak Japan, India, Colombia; Portugal partial). Run scripts/probe-ticketmaster-coverage.cjs before relying on it.
A13: predicthq | B13: PredictHQ | C13: https://www.predicthq.com/ | D13: API only; internal signal (never displayed) | E13: partner api | F13: api | G13: global | H13: event | I13: everything else | J13: restricted | K13: held (PREDICTHQ_API_KEY) | L13: live (trend engine) | P13: no | Q13: Terms forbid public display in raw form. Internal signal only (TravelPulse). Not a source for the events strip or plan facts shown to travelers.
... A21: kyoto_stop_official | B21: Temple / shrine / museum official pages (one row per stop when registered) | C21: (per stop) | D21: per stop, e.g. https://inari.jp/en/ ; https://www.kiyomizudera.or.jp/en/ ; https://www.shokoku-ji.jp/en/kinkakuji/ (hours/admission pages on each) | E21: official | F21: tavily_extract | G21: kyoto | H21: stop.hours, stop.ticketing | I21: everything else | J21: official | K21: n/a | L21: n/a | P21: no | Q21: Template row. Each registered stop page becomes its own row (e.g. Fushimi Inari, Kiyomizu-dera, Kinkaku-ji). Extract, never crawl; TTL 7 days for hours.
A22: kyoto_editorial_1 | B22: Editorial local #1 (to choose) | D22: (to choose) — register the section index page (e.g. /kyoto/eat/), not the homepage | E22: editorial | F22: tavily_extract | G22: kyoto | H22: tip, neighbourhood, dining | I22: lodging, transport.intercity, stop.ticketing | J22: editorial | K22: n/a | L22: n/a | P22: no | Q22: Decision 4 in the brief. Candidates only after reading terms: a local English-language publication with a stable URL structure. Quotes capped by BLOG_QUOTE_MAX_CHARS; linked out, never republished.
A23: visitscotland | B23: VisitScotland | C23: https://www.visitscotland.com/ | D23: https://www.visitscotland.com/things-to-do/events ; https://www.visitscotland.com/places-to-go/edinburgh | E23: official | F23: tavily_extract | G23: edinburgh | H23: stop.hours, event, practicalities, neighbourhood | I23: lodging, dining, transport.intercity | J23: official | K23: n/a | L23: n/a | P23: no | Q23: Candidate; terms unchecked.
A24: lothian_buses | B24: Lothian Buses / Edinburgh Trams | C24: https://www.lothianbuses.com/ | D24: https://www.lothianbuses.com/timetables-and-maps/ | E24: official | F24: tavily_extract | G24: edinburgh | H24: transport.local | I24: everything else | J24: official | K24: n/a | L24: n/a | P24: no | Q24: Candidate; terms unchecked.
A25: scotrail | B25: ScotRail | C25: https://www.scotrail.co.uk/ | D25: https://www.scotrail.co.uk/plan-your-journey/timetables | E25: official | F25: tavily_extract | G25: edinburgh | H25: transport.intercity.rail | I25: everything else | J25: official | K25: n/a | L25: n/a | P25: no | Q25: Candidate; terms unchecked.
A26: visit_porto | B26: Visit Porto (official) | C26: https://visitporto.travel/ | D26: https://visitporto.travel/en-GB/agenda (events; verify path) ; https://visitporto.travel/en-GB/what-to-do | E26: official | F26: tavily_extract | G26: porto | H26: stop.hours, event, neighbourhood, practicalities | I26: lodging, dining, transport.intercity | J26: official | K26: n/a | L26: n/a | P26: no | Q26: Candidate; terms unchecked.
A27: porto_transit | B27: STCP / Metro do Porto | C27: https://www.metrodoporto.pt/ | D27: https://en.metrodoporto.pt/ (lines & schedules); STCP: https://www.stcp.pt/en/travel/ | E27: official | F27: tavily_extract | G27: porto | H27: transport.local | I27: everything else | J27: official | K27: n/a | L27: n/a | P27: no | Q27: Candidate; terms unchecked.
A28: cp_portugal | B28: CP — Comboios de Portugal | C28: https://www.cp.pt/ | D28: https://www.cp.pt/passageiros/en/train-times | E28: official | F28: tavily_extract | G28: porto | H28: transport.intercity.rail | I28: everything else | J28: official | K28: n/a | L28: n/a | P28: no | Q28: Candidate; terms unchecked.
A29: idt_bogota | B29: Instituto Distrital de Turismo (Bogotá) | C29: https://bogotadc.travel/ | D29: https://bogotadc.travel/en (events & things to do sections; verify paths) | E29: official | F29: tavily_extract | G29: bogota | H29: stop.hours, event, neighbourhood, practicalities | I29: lodging, dining, transport.intercity | J29: official | K29: n/a | L29: n/a | P29: no | Q29: Candidate; terms unchecked.
A30: transmilenio | B30: TransMilenio | C30: https://www.transmilenio.gov.co/ | D30: https://www.transmilenio.gov.co/loader.php?lServicio=Rutas (routes; verify) | E30: official | F30: tavily_extract | G30: bogota | H30: transport.local | I30: everything else | J30: official | K30: n/a | L30: n/a | P30: no | Q30: Candidate; terms unchecked.
A31: cartagena_tourism | B31: Corporación Turismo Cartagena de Indias | C31: https://cartagenadeindias.travel/ | D31: https://cartagenadeindias.travel/ (events & sites sections; verify paths) | E31: official | F31: tavily_extract | G31: cartagena | H31: stop.hours, event, neighbourhood, practicalities | I31: lodging, dining, transport.intercity | J31: official | K31: n/a | L31: n/a | P31: no | Q31: Candidate; terms unchecked.
A32: incredible_india | B32: Incredible India (Ministry of Tourism) | C32: https://www.incredibleindia.gov.in/ | D32: https://www.incredibleindia.gov.in/en/destinations (state/city pages) | E32: official | F32: tavily_extract | G32: mumbai, goa, jaipur | H32: practicalities, event, stop.hours | I32: lodging, dining, transport.local | J32: official | K32: n/a | L32: n/a | P32: no | Q32: Candidate; terms unchecked.
A33: irctc | B33: IRCTC (Indian Railways) | C33: https://www.irctc.co.in/ | D33: n/a — reference only; no automated access | E33: official | F33: manual | G33: mumbai, goa, jaipur | H33: transport.intercity.rail | I33: everything else | J33: restricted | K33: n/a | L33: no public API for third parties | P33: no | Q33: Automated access is restricted; 12Go resells Indian rail. Keep as reference only; do not crawl.
A34: goa_tourism | B34: Goa Tourism (GTDC) | C34: https://goa-tourism.com/ | D34: https://goa-tourism.com/ (events & places sections; verify paths) | E34: official | F34: tavily_extract | G34: goa | H34: stop.hours, event, practicalities | I34: lodging, dining, transport.intercity | J34: official | K34: n/a | L34: n/a | P34: no | Q34: Candidate; terms unchecked. Sunburn dates come from the organiser, not here.
A35: rtdc_rajasthan | B35: Rajasthan Tourism (RTDC) | C35: https://www.tourism.rajasthan.gov.in/ | D35: https://www.tourism.rajasthan.gov.in/jaipur.html (verify) | E35: official | F35: tavily_extract | G35: jaipur | H35: stop.hours, event, practicalities | I35: lodging, dining, transport.intercity | J35: official | K35: n/a | L35: n/a | P35: no | Q35: Candidate; terms unchecked.

Sheet Coverage (Kyoto)
A1: need | B1: required for slice | C1: active sources covering it (Kyoto or global) | D1: status | E1: candidate sources (any status)
A2: lodging | B2: =INDEX(Needs!$C$2:$C$15,MATCH(A2,Needs!$A$2:$A$15,0)) -> yes | C2: =SUMPRODUCT(--ISNUMBER(SEARCH(A2,Sources!$H$2:$H$35)),--(ISNUMBER(SEARCH("kyoto",Sources!$G$2:$G$35))+ISNUMBER(SEARCH("global",Sources!$G$2:$G$35))>0),--(Sources!$P$2:$P$35="yes")) -> 0 | D2: =IF(AND(LEFT(B2,3)="yes",C2=0),"GAP",IF(C2=0,"uncovered","ok")) -> GAP | E2: =SUMPRODUCT(--ISNUMBER(SEARCH(A2,Sources!$H$2:$H$35)),--(ISNUMBER(SEARCH("kyoto",Sources!$G$2:$G$35))+ISNUMBER(SEARCH("global",Sources!$G$2:$G$35))>0)) -> 2
A3: transport.intercity | B3: =INDEX(Needs!$C$2:$C$15,MATCH(A3,Needs!$A$2:$A$15,0)) -> recommended | C3: =SUMPRODUCT(--ISNUMBER(SEARCH(A3,Sources!$H$2:$H$35)),--(ISNUMBER(SEARCH("kyoto",Sources!$G$2:$G$35))+ISNUMBER(SEARCH("global",Sources!$G$2:$G$35))>0),--(Sources!$P$2:$P$35="yes")) -> 0 | D3: =IF(AND(LEFT(B3,3)="yes",C3=0),"GAP",IF(C3=0,"uncovered","ok")) -> uncovered | E3: =SUMPRODUCT(--ISNUMBER(SEARCH(A3,Sources!$H$2:$H$35)),--(ISNUMBER(SEARCH("kyoto",Sources!$G$2:$G$35))+ISNUMBER(SEARCH("global",Sources!$G$2:$G$35))>0)) -> 5
A4: transport.intercity.rail | B4: =INDEX(Needs!$C$2:$C$15,MATCH(A4,Needs!$A$2:$A$15,0)) -> recommended | C4: =SUMPRODUCT(--ISNUMBER(SEARCH(A4,Sources!$H$2:$H$35)),--(ISNUMBER(SEARCH("kyoto",Sources!$G$2:$G$35))+ISNUMBER(SEARCH("global",Sources!$G$2:$G$35))>0),--(Sources!$P$2:$P$35="yes")) -> 0 | D4: =IF(AND(LEFT(B4,3)="yes",C4=0),"GAP",IF(C4=0,"uncovered","ok")) -> uncovered | E4: =SUMPRODUCT(--ISNUMBER(SEARCH(A4,Sources!$H$2:$H$35)),--(ISNUMBER(SEARCH("kyoto",Sources!$G$2:$G$35))+ISNUMBER(SEARCH("global",Sources!$G$2:$G$35))>0)) -> 4
A5: transport.intercity.bus | B5: =INDEX(Needs!$C$2:$C$15,MATCH(A5,Needs!$A$2:$A$15,0)) -> no | C5: =SUMPRODUCT(--ISNUMBER(SEARCH(A5,Sources!$H$2:$H$35)),--(ISNUMBER(SEARCH("kyoto",Sources!$G$2:$G$35))+ISNUMBER(SEARCH("global",Sources!$G$2:$G$35))>0),--(Sources!$P$2:$P$35="yes")) -> 0 | D5: =IF(AND(LEFT(B5,3)="yes",C5=0),"GAP",IF(C5=0,"uncovered","ok")) -> uncovered | E5: =SUMPRODUCT(--ISNUMBER(SEARCH(A5,Sources!$H$2:$H$35)),--(ISNUMBER(SEARCH("kyoto",Sources!$G$2:$G$35))+ISNUMBER(SEARCH("global",Sources!$G$2:$G$35))>0)) -> 1
A6: transport.intercity.ferry | B6: =INDEX(Needs!$C$2:$C$15,MATCH(A6,Needs!$A$2:$A$15,0)) -> no | C6: =SUMPRODUCT(--ISNUMBER(SEARCH(A6,Sources!$H$2:$H$35)),--(ISNUMBER(SEARCH("kyoto",Sources!$G$2:$G$35))+ISNUMBER(SEARCH("global",Sources!$G$2:$G$35))>0),--(Sources!$P$2:$P$35="yes")) -> 0 | D6: =IF(AND(LEFT(B6,3)="yes",C6=0),"GAP",IF(C6=0,"uncovered","ok")) -> uncovered | E6: =SUMPRODUCT(--ISNUMBER(SEARCH(A6,Sources!$H$2:$H$35)),--(ISNUMBER(SEARCH("kyoto",Sources!$G$2:$G$35))+ISNUMBER(SEARCH("global",Sources!$G$2:$G$35))>0)) -> 1
A7: transport.cruise | B7: =INDEX(Needs!$C$2:$C$15,MATCH(A7,Needs!$A$2:$A$15,0)) -> no | C7: =SUMPRODUCT(--ISNUMBER(SEARCH(A7,Sources!$H$2:$H$35)),--(ISNUMBER(SEARCH("kyoto",Sources!$G$2:$G$35))+ISNUMBER(SEARCH("global",Sources!$G$2:$G$35))>0),--(Sources!$P$2:$P$35="yes")) -> 0 | D7: =IF(AND(LEFT(B7,3)="yes",C7=0),"GAP",IF(C7=0,"uncovered","ok")) -> uncovered | E7: =SUMPRODUCT(--ISNUMBER(SEARCH(A7,Sources!$H$2:$H$35)),--(ISNUMBER(SEARCH("kyoto",Sources!$G$2:$G$35))+ISNUMBER(SEARCH("global",Sources!$G$2:$G$35))>0)) -> 0
A8: transport.local | B8: =INDEX(Needs!$C$2:$C$15,MATCH(A8,Needs!$A$2:$A$15,0)) -> yes | C8: =SUMPRODUCT(--ISNUMBER(SEARCH(A8,Sources!$H$2:$H$35)),--(ISNUMBER(SEARCH("kyoto",Sources!$G$2:$G$35))+ISNUMBER(SEARCH("global",Sources!$G$2:$G$35))>0),--(Sources!$P$2:$P$35="yes")) -> 0 | D8: =IF(AND(LEFT(B8,3)="yes",C8=0),"GAP",IF(C8=0,"uncovered","ok")) -> GAP | E8: =SUMPRODUCT(--ISNUMBER(SEARCH(A8,Sources!$H$2:$H$35)),--(ISNUMBER(SEARCH("kyoto",Sources!$G$2:$G$35))+ISNUMBER(SEARCH("global",Sources!$G$2:$G$35))>0)) -> 3
A9: stop.hours | B9: =INDEX(Needs!$C$2:$C$15,MATCH(A9,Needs!$A$2:$A$15,0)) -> yes | C9: =SUMPRODUCT(--ISNUMBER(SEARCH(A9,Sources!$H$2:$H$35)),--(ISNUMBER(SEARCH("kyoto",Sources!$G$2:$G$35))+ISNUMBER(SEARCH("global",Sources!$G$2:$G$35))>0),--(Sources!$P$2:$P$35="yes")) -> 0 | D9: =IF(AND(LEFT(B9,3)="yes",C9=0),"GAP",IF(C9=0,"uncovered","ok")) -> GAP | E9: =SUMPRODUCT(--ISNUMBER(SEARCH(A9,Sources!$H$2:$H$35)),--(ISNUMBER(SEARCH("kyoto",Sources!$G$2:$G$35))+ISNUMBER(SEARCH("global",Sources!$G$2:$G$35))>0)) -> 5
A10: stop.ticketing | B10: =INDEX(Needs!$C$2:$C$15,MATCH(A10,Needs!$A$2:$A$15,0)) -> yes | C10: =SUMPRODUCT(--ISNUMBER(SEARCH(A10,Sources!$H$2:$H$35)),--(ISNUMBER(SEARCH("kyoto",Sources!$G$2:$G$35))+ISNUMBER(SEARCH("global",Sources!$G$2:$G$35))>0),--(Sources!$P$2:$P$35="yes")) -> 0 | D10: =IF(AND(LEFT(B10,3)="yes",C10=0),"GAP",IF(C10=0,"uncovered","ok")) -> GAP | E10: =SUMPRODUCT(--ISNUMBER(SEARCH(A10,Sources!$H$2:$H$35)),--(ISNUMBER(SEARCH("kyoto",Sources!$G$2:$G$35))+ISNUMBER(SEARCH("global",Sources!$G$2:$G$35))>0)) -> 2
A11: dining | B11: =INDEX(Needs!$C$2:$C$15,MATCH(A11,Needs!$A$2:$A$15,0)) -> yes | C11: =SUMPRODUCT(--ISNUMBER(SEARCH(A11,Sources!$H$2:$H$35)),--(ISNUMBER(SEARCH("kyoto",Sources!$G$2:$G$35))+ISNUMBER(SEARCH("global",Sources!$G$2:$G$35))>0),--(Sources!$P$2:$P$35="yes")) -> 0 | D11: =IF(AND(LEFT(B11,3)="yes",C11=0),"GAP",IF(C11=0,"uncovered","ok")) -> GAP | E11: =SUMPRODUCT(--ISNUMBER(SEARCH(A11,Sources!$H$2:$H$35)),--(ISNUMBER(SEARCH("kyoto",Sources!$G$2:$G$35))+ISNUMBER(SEARCH("global",Sources!$G$2:$G$35))>0)) -> 2
A12: activity | B12: =INDEX(Needs!$C$2:$C$15,MATCH(A12,Needs!$A$2:$A$15,0)) -> yes (platform listings first) | C12: =SUMPRODUCT(--ISNUMBER(SEARCH(A12,Sources!$H$2:$H$35)),--(ISNUMBER(SEARCH("kyoto",Sources!$G$2:$G$35))+ISNUMBER(SEARCH("global",Sources!$G$2:$G$35))>0),--(Sources!$P$2:$P$35="yes")) -> 0 | D12: =IF(AND(LEFT(B12,3)="yes",C12=0),"GAP",IF(C12=0,"uncovered","ok")) -> GAP | E12: =SUMPRODUCT(--ISNUMBER(SEARCH(A12,Sources!$H$2:$H$35)),--(ISNUMBER(SEARCH("kyoto",Sources!$G$2:$G$35))+ISNUMBER(SEARCH("global",Sources!$G$2:$G$35))>0)) -> 5
A13: event | B13: =INDEX(Needs!$C$2:$C$15,MATCH(A13,Needs!$A$2:$A$15,0)) -> recommended | C13: =SUMPRODUCT(--ISNUMBER(SEARCH(A13,Sources!$H$2:$H$35)),--(ISNUMBER(SEARCH("kyoto",Sources!$G$2:$G$35))+ISNUMBER(SEARCH("global",Sources!$G$2:$G$35))>0),--(Sources!$P$2:$P$35="yes")) -> 0 | D13: =IF(AND(LEFT(B13,3)="yes",C13=0),"GAP",IF(C13=0,"uncovered","ok")) -> uncovered | E13: =SUMPRODUCT(--ISNUMBER(SEARCH(A13,Sources!$H$2:$H$35)),--(ISNUMBER(SEARCH("kyoto",Sources!$G$2:$G$35))+ISNUMBER(SEARCH("global",Sources!$G$2:$G$35))>0)) -> 5
... A15: neighbourhood | B15: =INDEX(Needs!$C$2:$C$15,MATCH(A15,Needs!$A$2:$A$15,0)) -> yes | C15: =SUMPRODUCT(--ISNUMBER(SEARCH(A15,Sources!$H$2:$H$35)),--(ISNUMBER(SEARCH("kyoto",Sources!$G$2:$G$35))+ISNUMBER(SEARCH("global",Sources!$G$2:$G$35))>0),--(Sources!$P$2:$P$35="yes")) -> 0 | D15: =IF(AND(LEFT(B15,3)="yes",C15=0),"GAP",IF(C15=0,"uncovered","ok")) -> GAP | E15: =SUMPRODUCT(--ISNUMBER(SEARCH(A15,Sources!$H$2:$H$35)),--(ISNUMBER(SEARCH("kyoto",Sources!$G$2:$G$35))+ISNUMBER(SEARCH("global",Sources!$G$2:$G$35))>0)) -> 4
A17: Every source ships with active = no, so every required need reads GAP until you check terms and flip rows to yes. That is the point: the report tells you what to do next. Column E shows how many candidates exist regardless of status.

Sheet Providers (recruiting)
A1: source_id | B1: market | C1: role (roles_needed key) | D1: where they are found | E1: lookup_url (where to look) | F1: kind | G1: outreach method | H1: in-platform path | I1: license / etiquette note | J1: contacted_at | K1: contacted_by | L1: outcome | M1: notes
A2: kyoto_licensed_guides | B2: kyoto | C2: tour_guide | D2: National Government Licensed Guide Interpreter registry (JNTO-listed associations, e.g. JFG / KSGG for Kansai) | E2: JNTO guide-interpreter search: https://www.japan.travel/en/plan/guide-services/ (verify); Kansai associations via that listing | F2: registry / association | G2: email the association; ask to circulate the Ways to earn page to Kyoto members | H2: /earn?role=service_provider (tour_guide) | I2: Licensed guides are the compliant in-person guiding role (expert catalog: in-person guiding is a provider role). Do not scrape member lists; ask the association to forward. | M2: Highest priority: the golden path's 'hand it to a local' and A6 suggestions need at least 2 approved guides with live listings.
A3: kyoto_city_certified_guides | B3: kyoto | C3: tour_guide | D3: Kyoto City Certified Tourist Guide programme (Kyoto Convention & Visitors Bureau) | E3: Kyoto CVB: https://www.kyoto.travel/en/ (guide programme page; verify path) | F3: registry | G3: contact KCVB; request introduction to certified guides interested in independent bookings | H3: /earn?role=service_provider (tour_guide) | I3: City programme; guides may be bound to KCVB booking channels. Ask before listing.
A4: kyoto_charter_taxi | B4: kyoto | C4: private_transportation | D4: MK Taxi / Yasaka Taxi charter desks; Kyoto Hire-Taxi Association | E4: https://www.mk-group.co.jp/english/ (charter); Yasaka: https://www.yasaka.jp/english/ (verify) | F4: operator / association | G4: direct email to charter desk; propose listing sightseeing charters as a bookable service | H4: /earn?role=service_provider (private_transportation) | I4: Charter fares are regulated; list published charter rates only. Drivers cannot be individually recruited off an operator.
A5: kyoto_photographers | B5: kyoto | C5: photography | D5: Independent photographers: Kyoto studios offering location shoots; JPS (Japan Professional Photographers Society) Kansai; Instagram location tags (manual, no scraping) | E5: manual: search 'Kyoto photographer location shoot English' ; JPS: https://www.jps.gr.jp/ (Japanese) | F5: association / manual | G5: personal outreach by DM or email with the storefront pitch; two or three named people, not a list | H5: /earn?role=service_provider (photography) | I5: No scraping of Instagram. One-to-one messages only; keep a log of who was contacted. | M5: Honeymoon / anniversary / proposal occasions all list photography in roles_needed.
A6: kyoto_activity_hosts | B6: kyoto | C6: activity_provider | D6: Tea ceremony, cooking class, kimono, craft workshop hosts (many already list on Viator / Klook / GetYourGuide) | E6: discovery: Viator/Klook/GetYourGuide Kyoto pages (see Sources content_url) | F6: partner listings (discovery only) | G6: find hosts via partner listings, then approach them directly for a Traveloure listing at their own price | H6: /earn?role=service_provider (activity_provider) | I6: Partner listings are for discovering who exists; the Traveloure listing is theirs, priced by them. Never copy a partner listing's text.
A7: kyoto_dining | B7: kyoto | C7: dining_venue | D7: Restaurants that take reservations for visitors (kaiseki, izakaya with English booking); reservation platforms (TableCheck, Omakase, Pocket Concierge) as discovery only | E7: discovery: https://www.tablecheck.com/en/kyoto ; https://pocket-concierge.jp/en/ (verify) — then go direct | F7: venue / platform (discovery only) | G7: approach venues directly; dining_venue listings hold a reservation policy and a price level, not a menu | H7: /earn?role=service_provider (dining_venue) | I7: Reservation platforms' terms forbid automated use; use them to find venues, then go direct. Expert nuggets carry reservation tips in plans. | M7: The 'dining' need has no content source; this is where it gets covered, one venue at a time plus expert tips.
A8: kyoto_golf | B8: kyoto | C8: activity_provider | D8: Golf courses within reach of Kyoto (course offices; JGTO-listed clubs); golf travel operators | E8: course sites via JGA course finder: https://www.jga.or.jp/ (Japanese); Kansai course lists on golf travel operators (discovery) | F8: venue / operator | G8: contact course offices for visitor tee-time policies; list as bookable where they allow third-party booking | H8: /earn?role=service_provider (activity_provider) | I8: Many private clubs require member introduction; list only courses that accept visitor bookings. golf-trip's primary anchor is the tee time (M7).
A9: kyoto_ryokan_direct | B9: kyoto | C9: accommodation | D9: Ryokan and small hotels that don't distribute through Booking.com (Kyoto Ryokan Association) | E9: Kyoto Ryokan Association: https://kyoto-ryokan.or.jp/ (verify; Japanese) | F9: association | G9: ask the association to circulate; ryokan list rooms with tier and house rules through the property form | H9: /earn?role=service_provider (accommodation) | I9: Properties set cancellation tier at property level (#1134). Rooms without tier inherit it. | M9: Only matters if Booking.com coverage stays thin; hotel_cache is the anchor source first.
A10: kyoto_concierge | B10: kyoto | C10: concierge_vip | D10: Hotel concierge alumni, bilingual coordinators, relocation consultants (Les Clefs d'Or Japan for introductions) | E10: Les Clefs d'Or Japan: https://www.lesclefsdor.jp/ (verify) | F10: association / manual | G10: personal introductions; this role overlaps the expert 'coordination' tier | H10: /earn?role=local_expert (coordination) or service_provider (concierge_vip) | I10: Reservation Lifeline and done-for-you booking are expert offerings; in-person accompaniment is a provider role. Point people to the right door.
A11: edinburgh_guides | B11: edinburgh | C11: tour_guide | D11: Scottish Tourist Guides Association (Blue Badge) | E11: https://www.stga.co.uk/ | F11: association | G11: email the association | H11: /earn?role=service_provider (tour_guide) | I11: Blue Badge is the recognised standard; ask the STGA to forward. | M11: Candidate; not contacted.
A12: porto_guides | B12: porto | C12: tour_guide | D12: Licensed guides via Turismo de Portugal registry (RNAAT operators; guia-intérprete) | E12: RNAAT registry: https://rnt.turismodeportugal.pt/ (verify); AGIC: https://www.agic.pt/ (verify) | F12: registry | G12: contact registered operators; individual guides via AGIC (Portuguese guides association) | H12: /earn?role=service_provider (tour_guide) | I12: RNAAT registration is the compliance marker for activity operators. | M12: Candidate; not contacted.
A13: bogota_guides | B13: bogota | C13: tour_guide | D13: Registro Nacional de Turismo (RNT) guides; Bogotá guide associations | E13: RNT: https://rnt.confecamaras.co/ (verify); IDT: https://bogotadc.travel/ | F13: registry | G13: contact via IDT or associations | H13: /earn?role=service_provider (tour_guide) | I13: RNT is mandatory for tourism services in Colombia; list only RNT-registered providers. | M13: Candidate; not contacted.
A14: cartagena_guides | B14: cartagena | C14: tour_guide | D14: RNT-registered guides and boat operators (Corporación Turismo Cartagena) | E14: RNT: https://rnt.confecamaras.co/ (verify); https://cartagenadeindias.travel/ | F14: registry | G14: contact via the corporation | H14: /earn?role=service_provider (tour_guide, private_transportation) | I14: RNT required. Boat trips to the islands are a transport + activity combination. | M14: Candidate; not contacted.
A15: india_guides | B15: mumbai, goa, jaipur | C15: tour_guide | D15: Ministry of Tourism Regional Level Guides (RLG) / IITFC-certified guides; state tourism guide lists | E15: Ministry of Tourism guide programme: https://tourism.gov.in/ (RLG / IITFC pages; verify) | F15: registry | G15: contact via state tourism offices and guide associations | H15: /earn?role=service_provider (tour_guide) | I15: Certified-guide lists exist per state; ask the office to circulate rather than copying lists. | M15: Candidate; not contacted.
A16: india_drivers | B16: mumbai, goa, jaipur | C16: private_transportation | D16: Tourist-permit car operators (state tourism approved); Goa taxi associations | E16: state tourism offices; Goa: https://goa-tourism.com/ (approved operators section; verify) | F16: operator / association | G16: direct to operators with tourist permits | H16: /earn?role=service_provider (private_transportation) | I16: List operators, not individual drivers; tourist permit required. | M16: Candidate; not contacted.
A17: all_markets_photographers | B17: all | C17: photography | D17: Local photographer associations; wedding/photo studios listed on partner sites (discovery only) | E17: per market, manual | F17: association / manual | G17: personal outreach, two or three per market | H17: /earn?role=service_provider (photography) | I17: No scraping; log contacts. | M17: Template row per market.
A18: all_markets_event_vendors | B18: all | C18: event_coordinator, caterer, florist, av_tech, rentals, venue | D18: Wedding/event vendor directories (discovery only), venue sales offices, hotel banquet teams | E18: per market, manual; venues first | F18: directory (discovery only) / venue | G18: direct outreach; venues first, vendors via venues | H18: /earn?role=service_provider (venue, event_coordinator, ...) | I18: Directories' terms forbid automated use; use for discovery, go direct. Hosted events and Celebrations groups are Track B. | M18: Template row per market; not needed for the Kyoto Trips slice.
